seo/__init__.py
seo/apps.py
seo/checks.py
seo/const.py
seo/context_processors.py
seo/middleware.py
seo/querysets.py
seo/services.py
seo/settings.py
seo/sitemaps.py
seo/translation.py
seo/utils.py
seo/admin/__init__.py
seo/admin/base_fields.py
seo/admin/filters.py
seo/admin/inline.py
seo/admin/mixins.py
seo/admin/model_instance_seo.py
seo/admin/url_seo.py
seo/admin/utils.py
seo/admin/view_seo.py
seo/locale/__init__.py
seo/locale/en/LC_MESSAGES/django.po
seo/locale/ru/LC_MESSAGES/django.po
seo/locale/uk/LC_MESSAGES/django.po
seo/migrations/0001_initial.py
seo/migrations/0002_auto_20200921_0601.py
seo/migrations/__init__.py
seo/mixins/__init__.py
seo/mixins/models.py
seo/mixins/views.py
seo/models/__init__.py
seo/models/base.py
seo/models/instance_based.py
seo/models/url_based.py
seo/models/view_based.py
seo/templates/admin/seo/url_seo.html
seo/templates/seo/seo.html
seo/templates/seo/jinja/seo.jinja
seo/templatetags/__init__.py
seo/templatetags/jinja_seo.py
seo/templatetags/seo.py
seo/tests/__init__.py
seo/tests/i18n_urls.py
seo/tests/settings.py
seo/tests/test_tags.py
seo/tests/test_utils.py
seo/tests/test_view_mixins.py
seo/tests/urls.py
django_ok_seo-0.9.4.dist-info/LICENSE
django_ok_seo-0.9.4.dist-info/METADATA
django_ok_seo-0.9.4.dist-info/WHEEL
django_ok_seo-0.9.4.dist-info/top_level.txt
django_ok_seo-0.9.4.dist-info/RECORD
