Metadata-Version: 2.1
Name: django-ok-seo
Version: 0.9.4
Summary: django-ok-seo allows you to add meta tags and OpenGraph properties to your HTML responses.
Home-page: https://github.com/LowerDeez/ok-seo
Author: Oleg Kleschunov
Author-email: igorkleschunov@gmail.com
License: MIT
Keywords: python,seo,seo-models,meta-tags,django,facebook,opengraph
Platform: UNKNOWN
Classifier: Development Status :: 4 - Beta
Classifier: Environment :: Web Environment
Classifier: Intended Audience :: Developers
Classifier: License :: OSI Approved :: MIT License
Classifier: Operating System :: OS Independent
Classifier: Programming Language :: Python
Classifier: Programming Language :: Python :: 3.6
Classifier: Programming Language :: Python :: 3.7
Classifier: Framework :: Django
Classifier: Framework :: Django :: 1.11
Classifier: Framework :: Django :: 2.0
Classifier: Framework :: Django :: 2.1
Classifier: Framework :: Django :: 2.2
License-File: LICENSE
Requires-Dist: django (>=1.11)
Requires-Dist: six
Requires-Dist: mock
